setup.cfg
setup.py
JSONBender.egg-info/PKG-INFO
JSONBender.egg-info/SOURCES.txt
JSONBender.egg-info/dependency_links.txt
JSONBender.egg-info/top_level.txt
jsonbender/__init__.py
jsonbender/_compat.py
jsonbender/core.py
jsonbender/list_ops.py
jsonbender/selectors.py
jsonbender/string_ops.py
jsonbender/test.py