Metadata-Version: 1.1
Name: JSONBender
Version: 0.7.1
Summary: Library for transforming JSON data between different formats.
Home-page: https://github.com/Onyo/jsonbender
Author: Elias Tandel
Author-email: backend@onyo.com
License: UNKNOWN
Download-URL: https://codeload.github.com/Onyo/jsonbender/tar.gz/0.7.1
Keywords: dsl,edsl,json
Platform: UNKNOWN
